MANIFEST.in
README.md
README.rst
setup.py
traitar/PhenotypeCollection.py
traitar/__init__.py
traitar/_version.py
traitar/domtblout2gene_generic.py
traitar/evaluation.py
traitar/get_external_data.py
traitar/heatmap.py
traitar/hmm2gff.py
traitar/hmmer2filtered_best.py
traitar/merge_preds.py
traitar/modify.py
traitar/predict.py
traitar/traitar
traitar.egg-info/PKG-INFO
traitar.egg-info/SOURCES.txt
traitar.egg-info/dependency_links.txt
traitar.egg-info/not-zip-safe
traitar.egg-info/requires.txt
traitar.egg-info/top_level.txt
traitar/data/colors.txt
traitar/data/models/phypat+PGL.tar.gz
traitar/data/models/phypat.tar.gz
traitar/data/sample_data/1457190.3.RefSeq.faa
traitar/data/sample_data/1457190.3.RefSeq.gff
traitar/data/sample_data/525367.9.RefSeq.faa
traitar/data/sample_data/525367.9.RefSeq.gff
traitar/data/sample_data/samples.txt
traitar/data/sample_data/samples_gene_gff.txt
traitar/data/sample_data/traitar_out/annotation/pfam/Listeria_grayi_DSM_20601_domtblout.dat
traitar/data/sample_data/traitar_out/annotation/pfam/Listeria_grayi_DSM_20601_filtered_best.dat
traitar/data/sample_data/traitar_out/annotation/pfam/Listeria_ivanovii_WSLC3009_domtblout.dat
traitar/data/sample_data/traitar_out/annotation/pfam/Listeria_ivanovii_WSLC3009_filtered_best.dat
traitar/data/sample_data/traitar_out/annotation/pfam/joblog_filter_and_aggregate.txt
traitar/data/sample_data/traitar_out/annotation/pfam/joblog_filter_and_aggregate_recompute.txt
traitar/data/sample_data/traitar_out/annotation/pfam/joblog_generate_annotation_matrix.txt
traitar/data/sample_data/traitar_out/annotation/pfam/joblog_hmmer.txt
traitar/data/sample_data/traitar_out/annotation/pfam/joblog_hmmer_recompute.txt
traitar/data/sample_data/traitar_out/annotation/pfam/summary.dat
traitar/data/sample_data/traitar_out/phenotype_prediction/feature_track_commands.txt
traitar/data/sample_data/traitar_out/phenotype_prediction/heatmap_combined.png
traitar/data/sample_data/traitar_out/phenotype_prediction/heatmap_phypat+PGL.png
traitar/data/sample_data/traitar_out/phenotype_prediction/heatmap_phypat.png
traitar/data/sample_data/traitar_out/phenotype_prediction/predictions_flat_majority-votes_combined.txt
