Metadata-Version: 1.0
Name: traitar
Version: 1.1.2
Summary: traitar - The microbial trait analyzer
Home-page: http://github.com/aweimann/traitar
Author: Aaron Weimann
Author-email: weimann@hhu.de
License: GNU General Public License, version 3 (GPL-3.0)
Platform: UNKNOWN
